ipymidicontrols/__init__.py
ipymidicontrols/_frontend.py
ipymidicontrols/_version.py
ipymidicontrols/xtouchmini.py
ipymidicontrols/labextension/jupyter-widgets-midicontrols-0.1.2.tgz
ipymidicontrols/nbextension/__init__.py
ipymidicontrols/nbextension/static/extension.js
ipymidicontrols/nbextension/static/index.js
ipymidicontrols/nbextension/static/index.js.map
ipymidicontrols/tests/__init__.py
ipymidicontrols/tests/conftest.py
ipymidicontrols/tests/test_example.py
ipymidicontrols/tests/test_nbextension_path.py
ipymidicontrols-0.1.3.data/data/etc/jupyter/nbconfig/notebook.d/ipymidicontrols.json
ipymidicontrols-0.1.3.data/data/share/jupyter/lab/extensions/jupyter-widgets-midicontrols-0.1.2.tgz
ipymidicontrols-0.1.3.data/data/share/jupyter/nbextensions/ipymidicontrols/extension.js
ipymidicontrols-0.1.3.data/data/share/jupyter/nbextensions/ipymidicontrols/index.js
ipymidicontrols-0.1.3.data/data/share/jupyter/nbextensions/ipymidicontrols/index.js.map
ipymidicontrols-0.1.3.dist-info/LICENSE.txt
ipymidicontrols-0.1.3.dist-info/METADATA
ipymidicontrols-0.1.3.dist-info/WHEEL
ipymidicontrols-0.1.3.dist-info/top_level.txt
ipymidicontrols-0.1.3.dist-info/RECORD
